{"lastModified":null,"uri":"c::22670744871::vessel::2a830130-dc48-11f0-8c4d-05177028b12d","yachtType":["Sailing","Catamaran"],"description":"Operating Area: Greece\n\nStandra is a spacious and modern Bali 4.6 catamaran designed for comfortable island cruising with larger groups. Her open-plan layout, multiple lounging areas, and excellent ventilation create a relaxed onboard atmosphere. Ideal for social sailing, long stays at anchor, and effortless exploration of the Ionian Sea in style.","blueprint":{"name":"STANDRA","images":["/media/media::image::a::vessel::2a830130-dc48-11f0-8c4d-05177028b12d::assets::ed4e4b60-dc49-11f0-ac8b-6de66180a2f8/{imageVariant}","/media/media::image::a::vessel::2a830130-dc48-11f0-8c4d-05177028b12d::assets::ed31e9c0-dc49-11f0-ac8b-6de66180a2f8/{imageVariant}","/media/media::image::a::vessel::2a830130-dc48-11f0-8c4d-05177028b12d::assets::ed2e8e60-dc49-11f0-ac8b-6de66180a2f8/{imageVariant}","/media/media::image::a::vessel::2a830130-dc48-11f0-8c4d-05177028b12d::assets::ed2e1930-dc49-11f0-ac8b-6de66180a2f8/{imageVariant}","/media/media::image::a::vessel::2a830130-dc48-11f0-8c4d-05177028b12d::assets::ed4f83e0-dc49-11f0-ac8b-6de66180a2f8/{imageVariant}","/media/media::image::a::vessel::2a830130-dc48-11f0-8c4d-05177028b12d::assets::ed4794a0-dc49-11f0-ac8b-6de66180a2f8/{imageVariant}","/media/media::image::a::vessel::2a830130-dc48-11f0-8c4d-05177028b12d::assets::ed4809d0-dc49-11f0-ac8b-6de66180a2f8/{imageVariant}","/media/media::image::a::vessel::2a830130-dc48-11f0-8c4d-05177028b12d::assets::ed4e9980-dc49-11f0-ac8b-6de66180a2f8/{imageVariant}","/media/media::image::a::vessel::2a830130-dc48-11f0-8c4d-05177028b12d::assets::ed4d8810-dc49-11f0-ac8b-6de66180a2f8/{imageVariant}","/media/media::image::a::vessel::2a830130-dc48-11f0-8c4d-05177028b12d::assets::ed4f0eb0-dc49-11f0-ac8b-6de66180a2f8/{imageVariant}","/media/media::image::a::vessel::2a830130-dc48-11f0-8c4d-05177028b12d::assets::ed49b780-dc49-11f0-ac8b-6de66180a2f8/{imageVariant}","/media/media::image::a::vessel::2a830130-dc48-11f0-8c4d-05177028b12d::assets::ed2f2aa0-dc49-11f0-ac8b-6de66180a2f8/{imageVariant}","/media/media::image::a::vessel::2a830130-dc48-11f0-8c4d-05177028b12d::assets::ed2f78c0-dc49-11f0-ac8b-6de66180a2f8/{imageVariant}","/media/media::image::a::vessel::2a830130-dc48-11f0-8c4d-05177028b12d::assets::ed487f00-dc49-11f0-ac8b-6de66180a2f8/{imageVariant}","/media/media::image::a::vessel::2a830130-dc48-11f0-8c4d-05177028b12d::assets::ed6b2230-dc49-11f0-ac8b-6de66180a2f8/{imageVariant}"],"make":"Bali Catamarans","model":"Bali 4.6","sleeps":12,"basePort":{"uri":"a::place::fcad4c70-5da8-11f0-9ece-3703daf477f7","name":"Lefkas Marina (D-Marin Lefkas)","coordinates":{"latitude":38.83012271322201,"longitude":20.71197411455054},"country":"Greece"},"builtYear":2021,"fuelCapacity":800,"cabinLayout":[],"cabins":5,"bathrooms":4,"length":14.33,"beam":7.62,"draft":1.22,"engines":"2x40 hp","amenities":[{"label":"Air Conditioning"},{"label":"Generator"},{"label":"Watermaker"},{"label":"Bimini"},{"label":"Cockpit cushions"},{"label":"Cockpit speakers"},{"label":"Coffee maker"},{"label":"Electric winches"},{"label":"Refrigerator"},{"label":"Heating"},{"label":"Ice maker"},{"label":"Sprayhood"},{"label":"Autopilot"},{"label":"Chart plotter"},{"label":"Lazy jack"},{"label":"Inverter"},{"label":"Solar Panels"},{"label":"USB Sockets"}],"toys":[{"label":"Dinghy with outboard engine"},{"label":"Stand up paddle"},{"label":"Snorkeling equipment"}],"entertainment":["Wi-Fi"]},"crew":[],"pricing":{"weekPricingFrom":{"currency":"EUR","price":249030,"displayCurrency":"EUR","displayPrice":249030,"unit":"WEEK"},"weekPricingTo":{"currency":"EUR","price":950040,"displayCurrency":"EUR","displayPrice":950040,"unit":"WEEK"},"pricingInfo":[{"name":"07.03.2026 - 11.04.2026","effectiveDates":[{"from":"2026-03-07T00:00:00.000Z","to":"2026-04-11T23:59:59.999Z"},{"from":"2027-03-07T00:00:00.000Z","to":"2027-04-11T23:59:59.999Z"},{"from":"2028-03-07T00:00:00.000Z","to":"2028-04-11T23:59:59.999Z"}],"pricing":{"currency":"EUR","charterFee":349020,"inputAmountTaxed":"NONE","note":"","unit":"WEEK","lineItems":[{"item":"Charter Fee","quantity":1,"unitPrice":387800,"amount":349020,"discount":{"type":"PERCENTAGE","value":0.1}}],"total":349020,"subTotal":349020,"totalTax":0},"inclusionZones":[{"label":"Greece","type":"Sovereign country","category":["Europe","Southern Europe","Greece"],"coordinates":[24.261736188816826,38.42232351533858],"bbox":[19.646484375,34.934472656249994,28.231835937500023,41.743798828124994]}],"exclusionZones":[],"petsAllowed":false},{"name":"11.04.2026 - 18.04.2026","effectiveDates":[{"from":"2026-04-11T00:00:00.000Z","to":"2026-04-18T23:59:59.999Z"},{"from":"2027-04-11T00:00:00.000Z","to":"2027-04-18T23:59:59.999Z"},{"from":"2028-04-11T00:00:00.000Z","to":"2028-04-18T23:59:59.999Z"}],"pricing":{"currency":"EUR","charterFee":249030,"inputAmountTaxed":"NONE","note":"","unit":"WEEK","lineItems":[{"item":"Charter Fee","quantity":1,"unitPrice":276700,"amount":249030,"discount":{"type":"PERCENTAGE","value":0.1}}],"total":249030,"subTotal":249030,"totalTax":0},"inclusionZones":[{"label":"Greece","type":"Sovereign country","category":["Europe","Southern Europe","Greece"],"coordinates":[24.261736188816826,38.42232351533858],"bbox":[19.646484375,34.934472656249994,28.231835937500023,41.743798828124994]}],"exclusionZones":[],"petsAllowed":false},{"name":"18.04.2026 - 25.04.2026","effectiveDates":[{"from":"2026-04-18T00:00:00.000Z","to":"2026-04-25T23:59:59.999Z"},{"from":"2027-04-18T00:00:00.000Z","to":"2027-04-25T23:59:59.999Z"},{"from":"2028-04-18T00:00:00.000Z","to":"2028-04-25T23:59:59.999Z"}],"pricing":{"currency":"EUR","charterFee":349020,"inputAmountTaxed":"NONE","note":"","unit":"WEEK","lineItems":[{"item":"Charter Fee","quantity":1,"unitPrice":387800,"amount":349020,"discount":{"type":"PERCENTAGE","value":0.1}}],"total":349020,"subTotal":349020,"totalTax":0},"inclusionZones":[{"label":"Greece","type":"Sovereign country","category":["Europe","Southern Europe","Greece"],"coordinates":[24.261736188816826,38.42232351533858],"bbox":[19.646484375,34.934472656249994,28.231835937500023,41.743798828124994]}],"exclusionZones":[],"petsAllowed":false},{"name":"25.04.2026 - 02.05.2026","effectiveDates":[{"from":"2026-04-25T00:00:00.000Z","to":"2026-05-02T23:59:59.999Z"},{"from":"2027-04-25T00:00:00.000Z","to":"2027-05-02T23:59:59.999Z"},{"from":"2028-04-25T00:00:00.000Z","to":"2028-05-02T23:59:59.999Z"}],"pricing":{"currency":"EUR","charterFee":249030,"inputAmountTaxed":"NONE","note":"","unit":"WEEK","lineItems":[{"item":"Charter Fee","quantity":1,"unitPrice":276700,"amount":249030,"discount":{"type":"PERCENTAGE","value":0.1}}],"total":249030,"subTotal":249030,"totalTax":0},"inclusionZones":[{"label":"Greece","type":"Sovereign country","category":["Europe","Southern Europe","Greece"],"coordinates":[24.261736188816826,38.42232351533858],"bbox":[19.646484375,34.934472656249994,28.231835937500023,41.743798828124994]}],"exclusionZones":[],"petsAllowed":false},{"name":"02.05.2026 - 09.05.2026","effectiveDates":[{"from":"2026-05-02T00:00:00.000Z","to":"2026-05-09T23:59:59.999Z"},{"from":"2027-05-02T00:00:00.000Z","to":"2027-05-09T23:59:59.999Z"},{"from":"2028-05-02T00:00:00.000Z","to":"2028-05-09T23:59:59.999Z"}],"pricing":{"currency":"EUR","charterFee":349020,"inputAmountTaxed":"NONE","note":"","unit":"WEEK","lineItems":[{"item":"Charter Fee","quantity":1,"unitPrice":387800,"amount":349020,"discount":{"type":"PERCENTAGE","value":0.1}}],"total":349020,"subTotal":349020,"totalTax":0},"inclusionZones":[{"label":"Greece","type":"Sovereign country","category":["Europe","Southern Europe","Greece"],"coordinates":[24.261736188816826,38.42232351533858],"bbox":[19.646484375,34.934472656249994,28.231835937500023,41.743798828124994]}],"exclusionZones":[],"petsAllowed":false},{"name":"09.05.2026 - 16.05.2026","effectiveDates":[{"from":"2026-05-09T00:00:00.000Z","to":"2026-05-16T23:59:59.999Z"},{"from":"2027-05-09T00:00:00.000Z","to":"2027-05-16T23:59:59.999Z"},{"from":"2028-05-09T00:00:00.000Z","to":"2028-05-16T23:59:59.999Z"}],"pricing":{"currency":"EUR","charterFee":398970,"inputAmountTaxed":"NONE","note":"","unit":"WEEK","lineItems":[{"item":"Charter Fee","quantity":1,"unitPrice":443300,"amount":398970,"discount":{"type":"PERCENTAGE","value":0.1}}],"total":398970,"subTotal":398970,"totalTax":0},"inclusionZones":[{"label":"Greece","type":"Sovereign country","category":["Europe","Southern Europe","Greece"],"coordinates":[24.261736188816826,38.42232351533858],"bbox":[19.646484375,34.934472656249994,28.231835937500023,41.743798828124994]}],"exclusionZones":[],"petsAllowed":false},{"name":"16.05.2026 - 23.05.2026","effectiveDates":[{"from":"2026-05-16T00:00:00.000Z","to":"2026-05-23T23:59:59.999Z"},{"from":"2027-05-16T00:00:00.000Z","to":"2027-05-23T23:59:59.999Z"},{"from":"2028-05-16T00:00:00.000Z","to":"2028-05-23T23:59:59.999Z"}],"pricing":{"currency":"EUR","charterFee":459990,"inputAmountTaxed":"NONE","note":"","unit":"WEEK","lineItems":[{"item":"Charter Fee","quantity":1,"unitPrice":511100,"amount":459990,"discount":{"type":"PERCENTAGE","value":0.1}}],"total":459990,"subTotal":459990,"totalTax":0},"inclusionZones":[{"label":"Greece","type":"Sovereign country","category":["Europe","Southern Europe","Greece"],"coordinates":[24.261736188816826,38.42232351533858],"bbox":[19.646484375,34.934472656249994,28.231835937500023,41.743798828124994]}],"exclusionZones":[],"petsAllowed":false},{"name":"23.05.2026 - 30.05.2026","effectiveDates":[{"from":"2026-05-23T00:00:00.000Z","to":"2026-05-30T23:59:59.999Z"},{"from":"2027-05-23T00:00:00.000Z","to":"2027-05-30T23:59:59.999Z"},{"from":"2028-05-23T00:00:00.000Z","to":"2028-05-30T23:59:59.999Z"}],"pricing":{"currency":"EUR","charterFee":579960,"inputAmountTaxed":"NONE","note":"","unit":"WEEK","lineItems":[{"item":"Charter Fee","quantity":1,"unitPrice":644400,"amount":579960,"discount":{"type":"PERCENTAGE","value":0.1}}],"total":579960,"subTotal":579960,"totalTax":0},"inclusionZones":[{"label":"Greece","type":"Sovereign country","category":["Europe","Southern Europe","Greece"],"coordinates":[24.261736188816826,38.42232351533858],"bbox":[19.646484375,34.934472656249994,28.231835937500023,41.743798828124994]}],"exclusionZones":[],"petsAllowed":false},{"name":"30.05.2026 - 06.06.2026","effectiveDates":[{"from":"2026-05-30T00:00:00.000Z","to":"2026-06-06T23:59:59.999Z"},{"from":"2027-05-30T00:00:00.000Z","to":"2027-06-06T23:59:59.999Z"},{"from":"2028-05-30T00:00:00.000Z","to":"2028-06-06T23:59:59.999Z"}],"pricing":{"currency":"EUR","charterFee":790020,"inputAmountTaxed":"NONE","note":"","unit":"WEEK","lineItems":[{"item":"Charter Fee","quantity":1,"unitPrice":877800,"amount":790020,"discount":{"type":"PERCENTAGE","value":0.1}}],"total":790020,"subTotal":790020,"totalTax":0},"inclusionZones":[{"label":"Greece","type":"Sovereign country","category":["Europe","Southern Europe","Greece"],"coordinates":[24.261736188816826,38.42232351533858],"bbox":[19.646484375,34.934472656249994,28.231835937500023,41.743798828124994]}],"exclusionZones":[],"petsAllowed":false},{"name":"06.06.2026 - 20.06.2026","effectiveDates":[{"from":"2026-06-06T00:00:00.000Z","to":"2026-06-20T23:59:59.999Z"},{"from":"2027-06-06T00:00:00.000Z","to":"2027-06-20T23:59:59.999Z"},{"from":"2028-06-06T00:00:00.000Z","to":"2028-06-20T23:59:59.999Z"}],"pricing":{"currency":"EUR","charterFee":950040,"inputAmountTaxed":"NONE","note":"","unit":"WEEK","lineItems":[{"item":"Charter Fee","quantity":1,"unitPrice":1055600,"amount":950040,"discount":{"type":"PERCENTAGE","value":0.1}}],"total":950040,"subTotal":950040,"totalTax":0},"inclusionZones":[{"label":"Greece","type":"Sovereign country","category":["Europe","Southern Europe","Greece"],"coordinates":[24.261736188816826,38.42232351533858],"bbox":[19.646484375,34.934472656249994,28.231835937500023,41.743798828124994]}],"exclusionZones":[],"petsAllowed":false}]}}