{"lastModified":1763459365092,"uri":"c::7819240034::vessel::902703a0-896a-11f0-bfe3-7debe88f1d78","yachtType":["Sailing"],"description":"Operating Area: Greece\n\nKOS 52.1 is a 16.28m / 52ft Catamaran Luxury Yacht built in 2026 by Sunreef Yachts. Sleeping 10 guests in 5 cabins.","blueprint":{"name":"KOS 52.1","images":["/media/media::image::c::7819240034::vessel::902703a0-896a-11f0-bfe3-7debe88f1d78::assets::47d39240-ba60-11f0-94a0-85f229bd049e/{imageVariant}","/media/media::image::c::7819240034::vessel::902703a0-896a-11f0-bfe3-7debe88f1d78::assets::46e3db10-ba60-11f0-94a0-85f229bd049e/{imageVariant}","/media/media::image::c::7819240034::vessel::902703a0-896a-11f0-bfe3-7debe88f1d78::assets::47065730-ba60-11f0-94a0-85f229bd049e/{imageVariant}","/media/media::image::c::7819240034::vessel::902703a0-896a-11f0-bfe3-7debe88f1d78::assets::46e847e0-ba60-11f0-94a0-85f229bd049e/{imageVariant}","/media/media::image::c::7819240034::vessel::902703a0-896a-11f0-bfe3-7debe88f1d78::assets::46e4ec80-ba60-11f0-94a0-85f229bd049e/{imageVariant}","/media/media::image::c::7819240034::vessel::902703a0-896a-11f0-bfe3-7debe88f1d78::assets::470a9cf0-ba60-11f0-94a0-85f229bd049e/{imageVariant}","/media/media::image::c::7819240034::vessel::902703a0-896a-11f0-bfe3-7debe88f1d78::assets::46e365e0-ba60-11f0-94a0-85f229bd049e/{imageVariant}","/media/media::image::c::7819240034::vessel::902703a0-896a-11f0-bfe3-7debe88f1d78::assets::46e11bf0-ba60-11f0-94a0-85f229bd049e/{imageVariant}","/media/media::image::c::7819240034::vessel::902703a0-896a-11f0-bfe3-7debe88f1d78::assets::46e42930-ba60-11f0-94a0-85f229bd049e/{imageVariant}","/media/media::image::c::7819240034::vessel::902703a0-896a-11f0-bfe3-7debe88f1d78::assets::46e2c9a0-ba60-11f0-94a0-85f229bd049e/{imageVariant}","/media/media::image::c::7819240034::vessel::902703a0-896a-11f0-bfe3-7debe88f1d78::assets::46e1b830-ba60-11f0-94a0-85f229bd049e/{imageVariant}","/media/media::image::c::7819240034::vessel::902703a0-896a-11f0-bfe3-7debe88f1d78::assets::46dfe370-ba60-11f0-94a0-85f229bd049e/{imageVariant}","/media/media::image::c::7819240034::vessel::902703a0-896a-11f0-bfe3-7debe88f1d78::assets::46e588c0-ba60-11f0-94a0-85f229bd049e/{imageVariant}","/media/media::image::c::7819240034::vessel::902703a0-896a-11f0-bfe3-7debe88f1d78::assets::46ed7800-ba60-11f0-94a0-85f229bd049e/{imageVariant}","/media/media::image::c::7819240034::vessel::902703a0-896a-11f0-bfe3-7debe88f1d78::assets::470d5c10-ba60-11f0-94a0-85f229bd049e/{imageVariant}"],"make":"Beneteau","model":"Oceanis 52","sleeps":6,"basePort":{"uri":"a::place::5e595eb8-b3ed-11ed-be02-325096b39f47","name":"Athens","coordinates":{"latitude":37.986174,"longitude":23.7268443},"country":"Greece"},"builtYear":2026,"fuelCapacity":400,"cabinLayout":[],"cabins":5,"length":16.28,"beam":4.84,"draft":2.36,"engines":"1 x 110 HP ","amenities":[{"label":"Autopilot"},{"label":"Bow thruster"},{"label":"Electronic sea charts"},{"label":"GPS chart plotter"},{"label":"Heating"},{"label":"Solar panels"},{"label":"Bimini top"},{"label":"Sprayhood"}]},"crew":[],"pricing":{"weekPricingFrom":{"currency":"EUR","price":427500,"displayCurrency":"EUR","displayPrice":427500,"unit":"WEEK"},"weekPricingTo":{"currency":"EUR","price":902500,"displayCurrency":"EUR","displayPrice":902500,"unit":"WEEK"},"pricingInfo":[{"name":"01/01/2026 - 24/04/2026","effectiveDates":[{"from":"2026-01-01T00:00:00.000Z","to":"2026-04-24T23:59:59.999Z"}],"pricing":{"currency":"EUR","charterFee":427500,"inputAmountTaxed":"INCLUSIVE","note":"","unit":"WEEK","lineItems":[{"item":"Charter Fee","quantity":1,"unitPrice":450000,"amount":427500,"conditions":"","discount":{"type":"PERCENTAGE","value":0.05},"taxRate":{"label":"VAT","value":0.12}},{"item":"Security deposit","conditions":"","quantity":0,"unitPrice":350000,"amount":0}],"total":427500,"subTotal":427500,"totalTax":51300},"inclusionZones":[{"label":"Greece","type":"Sovereign country","category":["Europe","Southern Europe","Greece"],"coordinates":[24.261736188816826,38.42232351533858],"bbox":[19.646484375,34.934472656249994,28.231835937500023,41.743798828124994]}],"exclusionZones":[],"petsAllowed":true},{"name":"25/04/2026 - 22/05/2026 & 26/09/2026 - 31/12/2026","effectiveDates":[{"from":"2026-04-25T00:00:00.000Z","to":"2026-05-22T23:59:59.999Z"},{"from":"2026-09-26T00:00:00.000Z","to":"2026-12-31T23:59:59.999Z"}],"pricing":{"currency":"EUR","charterFee":560500,"inputAmountTaxed":"INCLUSIVE","note":"","unit":"WEEK","lineItems":[{"item":"Charter Fee","quantity":1,"unitPrice":590000,"amount":560500,"conditions":"","discount":{"type":"PERCENTAGE","value":0.05},"taxRate":{"label":"VAT","value":0.12}},{"item":"Security deposit","conditions":"","quantity":0,"unitPrice":350000,"amount":0}],"total":560500,"subTotal":560500,"totalTax":67260},"inclusionZones":[{"label":"Greece","type":"Sovereign country","category":["Europe","Southern Europe","Greece"],"coordinates":[24.261736188816826,38.42232351533858],"bbox":[19.646484375,34.934472656249994,28.231835937500023,41.743798828124994]}],"exclusionZones":[],"petsAllowed":true},{"name":"23/05/2026 - 12/06/2026 & 22/08/2026 - 25/09/2026","effectiveDates":[{"from":"2026-05-23T00:00:00.000Z","to":"2026-06-12T23:59:59.999Z"},{"from":"2026-08-22T00:00:00.000Z","to":"2026-09-25T23:59:59.999Z"}],"pricing":{"currency":"EUR","charterFee":722000,"inputAmountTaxed":"INCLUSIVE","note":"","unit":"WEEK","lineItems":[{"item":"Charter Fee","quantity":1,"unitPrice":760000,"amount":722000,"conditions":"","discount":{"type":"PERCENTAGE","value":0.05},"taxRate":{"label":"VAT","value":0.12}},{"item":"Security deposit","conditions":"","quantity":0,"unitPrice":350000,"amount":0}],"total":722000,"subTotal":722000,"totalTax":86640},"inclusionZones":[{"label":"Greece","type":"Sovereign country","category":["Europe","Southern Europe","Greece"],"coordinates":[24.261736188816826,38.42232351533858],"bbox":[19.646484375,34.934472656249994,28.231835937500023,41.743798828124994]}],"exclusionZones":[],"petsAllowed":true},{"name":"13/06/2026 - 24/07/2026","effectiveDates":[{"from":"2026-06-13T00:00:00.000Z","to":"2026-07-24T23:59:59.999Z"}],"pricing":{"currency":"EUR","charterFee":798000,"inputAmountTaxed":"INCLUSIVE","note":"","unit":"WEEK","lineItems":[{"item":"Charter Fee","quantity":1,"unitPrice":840000,"amount":798000,"conditions":"","discount":{"type":"PERCENTAGE","value":0.05},"taxRate":{"label":"VAT","value":0.12}},{"item":"Security deposit","conditions":"","quantity":0,"unitPrice":350000,"amount":0}],"total":798000,"subTotal":798000,"totalTax":95760},"inclusionZones":[{"label":"Greece","type":"Sovereign country","category":["Europe","Southern Europe","Greece"],"coordinates":[24.261736188816826,38.42232351533858],"bbox":[19.646484375,34.934472656249994,28.231835937500023,41.743798828124994]}],"exclusionZones":[],"petsAllowed":true},{"name":"25/07/2026 - 21/08/2026","effectiveDates":[{"from":"2026-07-25T00:00:00.000Z","to":"2026-08-21T23:59:59.999Z"}],"pricing":{"currency":"EUR","charterFee":902500,"inputAmountTaxed":"INCLUSIVE","note":"","unit":"WEEK","lineItems":[{"item":"Charter Fee","quantity":1,"unitPrice":950000,"amount":902500,"conditions":"","discount":{"type":"PERCENTAGE","value":0.05},"taxRate":{"label":"VAT","value":0.12}},{"item":"Security deposit","conditions":"","quantity":0,"unitPrice":350000,"amount":0}],"total":902500,"subTotal":902500,"totalTax":108300},"inclusionZones":[{"label":"Greece","type":"Sovereign country","category":["Europe","Southern Europe","Greece"],"coordinates":[24.261736188816826,38.42232351533858],"bbox":[19.646484375,34.934472656249994,28.231835937500023,41.743798828124994]}],"exclusionZones":[],"petsAllowed":true}]}}