{"lastModified":1775128668047,"uri":"c::39480359087::vessel::acd344f0-08d1-11f1-94a4-0be90c8f6f92","yachtType":["Motor"],"description":"Operating Area: Ortygia/Syracuse or Brucoli Bay, Santa Croce Cape, Green Water Bay, Landlord of the Turks, Arcile Bay \n\nSunseeker 75 is a sleek and powerful yacht, measuring 22 meters in length powered by twin 1300 hp MAN engines, it offers both speed and smooth daily cruising in Sicily. Its refined interior features two wide cabins, including a spacious master suite, two bathrooms, and a large, elegant salon. All areas are fully air-conditioned, and generators ensure comfort at all times. This yacht blends performance, luxury design, perfect for stylish and comfortable cruising.","blueprint":{"name":"ANITA II","images":["/media/media::image::a::vessel::acd344f0-08d1-11f1-94a4-0be90c8f6f92::assets::48c735e0-08d4-11f1-8df4-e73fb2b54ce6/{imageVariant}","/media/media::image::a::vessel::acd344f0-08d1-11f1-94a4-0be90c8f6f92::assets::48b90510-08d4-11f1-8df4-e73fb2b54ce6/{imageVariant}","/media/media::image::a::vessel::acd344f0-08d1-11f1-94a4-0be90c8f6f92::assets::48c9cdf0-08d4-11f1-8df4-e73fb2b54ce6/{imageVariant}","/media/media::image::a::vessel::acd344f0-08d1-11f1-94a4-0be90c8f6f92::assets::48b8de00-08d4-11f1-8df4-e73fb2b54ce6/{imageVariant}","/media/media::image::a::vessel::acd344f0-08d1-11f1-94a4-0be90c8f6f92::assets::48c8e390-08d4-11f1-8df4-e73fb2b54ce6/{imageVariant}","/media/media::image::a::vessel::acd344f0-08d1-11f1-94a4-0be90c8f6f92::assets::48c8e391-08d4-11f1-8df4-e73fb2b54ce6/{imageVariant}","/media/media::image::a::vessel::acd344f0-08d1-11f1-94a4-0be90c8f6f92::assets::48b7cc90-08d4-11f1-8df4-e73fb2b54ce6/{imageVariant}","/media/media::image::a::vessel::acd344f0-08d1-11f1-94a4-0be90c8f6f92::assets::48b841c0-08d4-11f1-8df4-e73fb2b54ce6/{imageVariant}","/media/media::image::a::vessel::acd344f0-08d1-11f1-94a4-0be90c8f6f92::assets::48c89570-08d4-11f1-8df4-e73fb2b54ce6/{imageVariant}","/media/media::image::a::vessel::acd344f0-08d1-11f1-94a4-0be90c8f6f92::assets::48c9a6e0-08d4-11f1-8df4-e73fb2b54ce6/{imageVariant}","/media/media::image::a::vessel::acd344f0-08d1-11f1-94a4-0be90c8f6f92::assets::48c84750-08d4-11f1-8df4-e73fb2b54ce6/{imageVariant}","/media/media::image::a::vessel::acd344f0-08d1-11f1-94a4-0be90c8f6f92::assets::48b81ab0-08d4-11f1-8df4-e73fb2b54ce6/{imageVariant}","/media/media::image::a::vessel::acd344f0-08d1-11f1-94a4-0be90c8f6f92::assets::48b868d0-08d4-11f1-8df4-e73fb2b54ce6/{imageVariant}"],"make":"Sunseeker","model":"Sunseeker 75 Predator","maxCrew":2,"sleeps":8,"basePort":{"uri":"a::place::27c284b4-b3ee-11ed-85e0-325096b39f47","name":"Sicily","coordinates":{"latitude":37.58501078938525,"longitude":14.12769674022258},"country":"Italy"},"cruisingCapacity":10,"staticCapacity":10,"builtYear":2007,"architect":"Don Shead","topSpeed":36,"cruiseSpeed":12,"fuelCapacity":5000,"cabinLayout":[],"cabins":2,"bathrooms":2,"length":22.1,"beam":5.43,"draft":1.8,"hullType":"deep-V ","hullConstruction":"GFRP","engines":"Twin 1300 hp MAN ","amenities":[{"label":"Air Conditioning"},{"label":"Generators"},{"label":"Sun Lounge area"},{"label":"Front Sundeck"}],"toys":[{"label":"Snorkeling equipment","quantity":"6"}],"entertainment":["Audio system, indoor","Audio System, outdoor"]},"crew":[],"pricing":{"dayPricingFrom":{"currency":"EUR","price":280000,"displayCurrency":"EUR","displayPrice":280000,"unit":"DAY"},"dayPricingTo":{"currency":"EUR","price":280000,"displayCurrency":"EUR","displayPrice":280000,"unit":"DAY"},"pricingInfo":[{"name":"Full Day Rate","effectiveDates":[{"from":"2026-01-01T00:00:00.000Z","to":"2026-12-31T23:59:59.999Z"},{"from":"2027-01-01T00:00:00.000Z","to":"2027-12-31T23:59:59.999Z"},{"from":"2028-01-01T00:00:00.000Z","to":"2028-12-31T23:59:59.999Z"}],"pricing":{"currency":"EUR","charterFee":280000,"inputAmountTaxed":"EXCLUSIVE","note":"","unit":"DAY","lineItems":[{"item":"Charter Fee","quantity":1,"unitPrice":280000,"amount":280000,"conditions":"Tax no included"},{"item":"","conditions":"","quantity":0.3,"unitPrice":350000,"amount":105000}],"total":385000,"subTotal":385000,"totalTax":0},"inclusionZones":[{"label":"Catania, Sicily, Italy","type":"Custom Area","category":["Catania"],"coordinates":[15.0625,37.512499999999996],"bbox":[14.941667,37.408333,15.183333,37.616667]}],"exclusionZones":[],"petsAllowed":true}]}}