{"lastModified":1772788519136,"uri":"c::7579706445::vessel::b3e867c0-a339-11ee-8b91-932d31bc9202","yachtType":["Sailing"],"description":"Operating Area: Greece\n\nAboard the BAVARIA CRUISER 46 you can just let go and put your feet up. She is designed for this – the huge bathing platform is ideal for swimming, sunbathing, chilling out or just relaxing at sea-level.","blueprint":{"name":"ARTEMIS","images":["/media/media::image::c::7579706445::vessel::b3e867c0-a339-11ee-8b91-932d31bc9202::assets::c5a7dcc0-a339-11ee-8b91-932d31bc9202.jpeg/{imageVariant}","/media/media::image::c::7579706445::vessel::b3e867c0-a339-11ee-8b91-932d31bc9202::assets::c94045c0-a339-11ee-8b91-932d31bc9202.jpeg/{imageVariant}","/media/media::image::c::7579706445::vessel::b3e867c0-a339-11ee-8b91-932d31bc9202::assets::c93fd090-a339-11ee-8b91-932d31bc9202.jpeg/{imageVariant}","/media/media::image::c::7579706445::vessel::b3e867c0-a339-11ee-8b91-932d31bc9202::assets::c93e9810-a339-11ee-8b91-932d31bc9202.jpeg/{imageVariant}","/media/media::image::c::7579706445::vessel::b3e867c0-a339-11ee-8b91-932d31bc9202::assets::c93f3450-a339-11ee-8b91-932d31bc9202.jpeg/{imageVariant}","/media/media::image::c::7579706445::vessel::b3e867c0-a339-11ee-8b91-932d31bc9202::assets::d61afba0-a339-11ee-8b91-932d31bc9202.jpeg/{imageVariant}","/media/media::image::c::7579706445::vessel::b3e867c0-a339-11ee-8b91-932d31bc9202::assets::d61a5f60-a339-11ee-8b91-932d31bc9202.jpeg/{imageVariant}","/media/media::image::c::7579706445::vessel::b3e867c0-a339-11ee-8b91-932d31bc9202::assets::d6197500-a339-11ee-8b91-932d31bc9202.jpeg/{imageVariant}","/media/media::image::c::7579706445::vessel::b3e867c0-a339-11ee-8b91-932d31bc9202::assets::d8ffa500-a339-11ee-8b91-932d31bc9202.jpeg/{imageVariant}","/media/media::image::c::7579706445::vessel::b3e867c0-a339-11ee-8b91-932d31bc9202::assets::d8ff2fd0-a339-11ee-8b91-932d31bc9202.jpeg/{imageVariant}","/media/media::image::c::7579706445::vessel::b3e867c0-a339-11ee-8b91-932d31bc9202::assets::d9001a30-a339-11ee-8b91-932d31bc9202.jpeg/{imageVariant}","/media/media::image::c::7579706445::vessel::b3e867c0-a339-11ee-8b91-932d31bc9202::assets::dc0f2ef0-a339-11ee-8b91-932d31bc9202.jpeg/{imageVariant}","/media/media::image::c::7579706445::vessel::b3e867c0-a339-11ee-8b91-932d31bc9202::assets::dc0da850-a339-11ee-8b91-932d31bc9202.jpeg/{imageVariant}","/media/media::image::c::7579706445::vessel::b3e867c0-a339-11ee-8b91-932d31bc9202::assets::dc0ce500-a339-11ee-8b91-932d31bc9202.jpeg/{imageVariant}","/media/media::image::c::7579706445::vessel::b3e867c0-a339-11ee-8b91-932d31bc9202::assets::dc0e6ba0-a339-11ee-8b91-932d31bc9202.jpeg/{imageVariant}","/media/media::image::c::7579706445::vessel::b3e867c0-a339-11ee-8b91-932d31bc9202::assets::dc0eb9c0-a339-11ee-8b91-932d31bc9202.jpeg/{imageVariant}","/media/media::image::c::7579706445::vessel::b3e867c0-a339-11ee-8b91-932d31bc9202::assets::dc0f07e0-a339-11ee-8b91-932d31bc9202.jpeg/{imageVariant}","/media/media::image::c::7579706445::vessel::b3e867c0-a339-11ee-8b91-932d31bc9202::assets::dc0df670-a339-11ee-8b91-932d31bc9202.jpeg/{imageVariant}","/media/media::image::c::7579706445::vessel::b3e867c0-a339-11ee-8b91-932d31bc9202::assets::dd56a310-a339-11ee-8b91-932d31bc9202.jpeg/{imageVariant}"],"make":"","model":"Bavaria Cruiser 46","maxCrew":1,"sleeps":10,"basePort":{"uri":"a::place::5e595eb8-b3ed-11ed-be02-325096b39f47","name":"Athens","coordinates":{"latitude":37.986174,"longitude":23.7268443},"country":"Greece"},"builtYear":2014,"topSpeed":"","cruiseSpeed":7,"fuelCapacity":210,"cabins":4,"bathrooms":3,"decks":"","length":13.6,"beam":4.35,"draft":1.73,"hullType":"","amenities":[{"label":"Bow Thruster","quantity":1},{"label":"Cockpit Cushions","quantity":1},{"label":"Cockpit Speakers","quantity":1},{"label":"Fans in Cabins","quantity":1},{"label":"Music Player","quantity":1},{"label":"Saloon Speakers","quantity":1},{"label":"Solar Panels","quantity":1},{"label":"Usb Charging Ports Saloon","quantity":1},{"label":"Swimming Ladder","quantity":1},{"label":"Auto Pilot","quantity":1},{"label":"VHF","quantity":1},{"label":"Refrigerator","quantity":1},{"label":"Gas Stove with Burners & Grill","quantity":1},{"label":"Bimini Top","quantity":1},{"label":"Bathing Platform","quantity":1}],"toys":[{"label":"Snorkelling Sets","quantity":1},{"label":"Dinghy","quantity":1}],"entertainment":["Music Player","Cockpit Speakers","Saloon Speakers"]},"crew":[],"pricing":{"weekPricingFrom":{"currency":"EUR","price":200000,"displayCurrency":"EUR","displayPrice":200000,"unit":"WEEK"},"weekPricingTo":{"currency":"EUR","price":530000,"displayCurrency":"EUR","displayPrice":530000,"unit":"WEEK"},"pricingInfo":[{"name":"01/01 -27/04","effectiveDates":[{"from":"2024-01-01T00:00:00.000Z","to":"2024-04-27T23:59:59.999Z"},{"from":"2025-01-01T00:00:00.000Z","to":"2025-04-27T23:59:59.999Z"},{"from":"2026-01-01T00:00:00.000Z","to":"2026-04-27T23:59:59.999Z"}],"pricing":{"note":"CHARTER RATES INCLUDE\nUse of yacht with her equipment • Yacht Insurance • VAT at current rate (discounted to 12%, subject to conditions) • Clean Linens (bed sheets & bath towels, 1 set per person per week, for up to 2 weeks max) • Outboard motor & first fill of gasoline • 1x full spare bottle of cooking gas • Berthing fees for first & last night at the marina/port • Final cleaning.","currency":"EUR","inputAmountTaxed":"INCLUSIVE","subTotal":200000,"totalTax":24000,"total":200000,"lineItems":[{"item":"Charter Fee","conditions":"","quantity":1,"unitPrice":200000,"amount":200000,"taxRate":{"label":"VAT","value":0.12}},{"item":"APA","conditions":"","quantity":0,"unitPrice":0,"amount":0},{"item":"Crew","conditions":"","quantity":0,"unitPrice":0,"amount":0},{"item":"Security Deposit","conditions":"","quantity":0,"unitPrice":300000,"amount":0}],"charterFee":200000,"unit":"WEEK"},"inclusionZones":[{"label":"Greece","type":"Sovereign country","category":["Europe","Southern Europe","Greece"],"coordinates":[24.261736188816826,38.42232351533858],"bbox":[19.646484375,34.934472656249994,28.231835937500023,41.743798828124994]}],"exclusionZones":[]},{"name":"27/04 -25/05","effectiveDates":[{"from":"2024-04-27T00:00:00.000Z","to":"2024-05-25T23:59:59.999Z"},{"from":"2025-04-27T00:00:00.000Z","to":"2025-05-25T23:59:59.999Z"},{"from":"2026-04-27T00:00:00.000Z","to":"2026-05-25T23:59:59.999Z"}],"pricing":{"note":"CHARTER RATES INCLUDE\nUse of yacht with her equipment • Yacht Insurance • VAT at current rate (discounted to 12%, subject to conditions) • Clean Linens (bed sheets & bath towels, 1 set per person per week, for up to 2 weeks max) • Outboard motor & first fill of gasoline • 1x full spare bottle of cooking gas • Berthing fees for first & last night at the marina/port • Final cleaning.","currency":"EUR","inputAmountTaxed":"INCLUSIVE","subTotal":295000,"totalTax":35400,"total":295000,"lineItems":[{"item":"Charter Fee","conditions":"","quantity":1,"unitPrice":295000,"amount":295000,"taxRate":{"label":"VAT","value":0.12}},{"item":"APA","conditions":"","quantity":0,"unitPrice":0,"amount":0},{"item":"Crew","conditions":"","quantity":0,"unitPrice":0,"amount":0},{"item":"Security Deposit","conditions":"","quantity":0,"unitPrice":300000,"amount":0}],"charterFee":295000,"unit":"WEEK"},"inclusionZones":[{"label":"Greece","type":"Sovereign country","category":["Europe","Southern Europe","Greece"],"coordinates":[24.261736188816826,38.42232351533858],"bbox":[19.646484375,34.934472656249994,28.231835937500023,41.743798828124994]}],"exclusionZones":[]},{"name":"25/05 -22/06","effectiveDates":[{"from":"2024-05-25T00:00:00.000Z","to":"2024-06-22T23:59:59.999Z"},{"from":"2025-05-25T00:00:00.000Z","to":"2025-06-22T23:59:59.999Z"},{"from":"2026-05-25T00:00:00.000Z","to":"2026-06-22T23:59:59.999Z"}],"pricing":{"note":"CHARTER RATES INCLUDE\nUse of yacht with her equipment • Yacht Insurance • VAT at current rate (discounted to 12%, subject to conditions) • Clean Linens (bed sheets & bath towels, 1 set per person per week, for up to 2 weeks max) • Outboard motor & first fill of gasoline • 1x full spare bottle of cooking gas • Berthing fees for first & last night at the marina/port • Final cleaning.","currency":"EUR","inputAmountTaxed":"INCLUSIVE","subTotal":395000,"totalTax":47400,"total":395000,"lineItems":[{"item":"Charter Fee","conditions":"","quantity":1,"unitPrice":395000,"amount":395000,"taxRate":{"label":"VAT","value":0.12}},{"item":"APA","conditions":"","quantity":0,"unitPrice":0,"amount":0},{"item":"Crew","conditions":"","quantity":0,"unitPrice":0,"amount":0},{"item":"Security Deposit","conditions":"","quantity":0,"unitPrice":300000,"amount":0}],"charterFee":395000,"unit":"WEEK"},"inclusionZones":[{"label":"Greece","type":"Sovereign country","category":["Europe","Southern Europe","Greece"],"coordinates":[24.261736188816826,38.42232351533858],"bbox":[19.646484375,34.934472656249994,28.231835937500023,41.743798828124994]}],"exclusionZones":[]},{"name":"22/06 -03/08","effectiveDates":[{"from":"2024-06-22T00:00:00.000Z","to":"2024-08-03T23:59:59.999Z"},{"from":"2025-06-22T00:00:00.000Z","to":"2025-08-03T23:59:59.999Z"},{"from":"2026-06-22T00:00:00.000Z","to":"2026-08-03T23:59:59.999Z"}],"pricing":{"note":"CHARTER RATES INCLUDE\nUse of yacht with her equipment • Yacht Insurance • VAT at current rate (discounted to 12%, subject to conditions) • Clean Linens (bed sheets & bath towels, 1 set per person per week, for up to 2 weeks max) • Outboard motor & first fill of gasoline • 1x full spare bottle of cooking gas • Berthing fees for first & last night at the marina/port • Final cleaning.","currency":"EUR","inputAmountTaxed":"INCLUSIVE","subTotal":445000,"totalTax":53400,"total":445000,"lineItems":[{"item":"Charter Fee","conditions":"","quantity":1,"unitPrice":445000,"amount":445000,"taxRate":{"label":"VAT","value":0.12}},{"item":"APA","conditions":"","quantity":0,"unitPrice":0,"amount":0},{"item":"Crew","conditions":"","quantity":0,"unitPrice":0,"amount":0},{"item":"Security Deposit","conditions":"","quantity":0,"unitPrice":300000,"amount":0}],"charterFee":445000,"unit":"WEEK"},"inclusionZones":[{"label":"Greece","type":"Sovereign country","category":["Europe","Southern Europe","Greece"],"coordinates":[24.261736188816826,38.42232351533858],"bbox":[19.646484375,34.934472656249994,28.231835937500023,41.743798828124994]}],"exclusionZones":[]},{"name":"03/08 -24/08","effectiveDates":[{"from":"2024-08-03T00:00:00.000Z","to":"2024-08-24T23:59:59.999Z"},{"from":"2025-08-03T00:00:00.000Z","to":"2025-08-24T23:59:59.999Z"},{"from":"2026-08-03T00:00:00.000Z","to":"2026-08-24T23:59:59.999Z"}],"pricing":{"note":"CHARTER RATES INCLUDE\nUse of yacht with her equipment • Yacht Insurance • VAT at current rate (discounted to 12%, subject to conditions) • Clean Linens (bed sheets & bath towels, 1 set per person per week, for up to 2 weeks max) • Outboard motor & first fill of gasoline • 1x full spare bottle of cooking gas • Berthing fees for first & last night at the marina/port • Final cleaning.","currency":"EUR","inputAmountTaxed":"INCLUSIVE","subTotal":530000,"totalTax":63600,"total":530000,"lineItems":[{"item":"Charter Fee","conditions":"","quantity":1,"unitPrice":530000,"amount":530000,"taxRate":{"label":"VAT","value":0.12}},{"item":"APA","conditions":"","quantity":0,"unitPrice":0,"amount":0},{"item":"Crew","conditions":"","quantity":0,"unitPrice":0,"amount":0},{"item":"Security Deposit","conditions":"","quantity":0,"unitPrice":300000,"amount":0}],"charterFee":530000,"unit":"WEEK"},"inclusionZones":[{"label":"Greece","type":"Sovereign country","category":["Europe","Southern Europe","Greece"],"coordinates":[24.261736188816826,38.42232351533858],"bbox":[19.646484375,34.934472656249994,28.231835937500023,41.743798828124994]}],"exclusionZones":[]},{"name":"24/08 -14/09","effectiveDates":[{"from":"2024-08-24T00:00:00.000Z","to":"2024-09-14T23:59:59.999Z"},{"from":"2025-08-24T00:00:00.000Z","to":"2025-09-14T23:59:59.999Z"},{"from":"2026-08-24T00:00:00.000Z","to":"2026-09-14T23:59:59.999Z"}],"pricing":{"note":"CHARTER RATES INCLUDE\nUse of yacht with her equipment • Yacht Insurance • VAT at current rate (discounted to 12%, subject to conditions) • Clean Linens (bed sheets & bath towels, 1 set per person per week, for up to 2 weeks max) • Outboard motor & first fill of gasoline • 1x full spare bottle of cooking gas • Berthing fees for first & last night at the marina/port • Final cleaning.","currency":"EUR","inputAmountTaxed":"INCLUSIVE","subTotal":445000,"totalTax":53400,"total":445000,"lineItems":[{"item":"Charter Fee","conditions":"","quantity":1,"unitPrice":445000,"amount":445000,"taxRate":{"label":"VAT","value":0.12}},{"item":"APA","conditions":"","quantity":0,"unitPrice":0,"amount":0},{"item":"Crew","conditions":"","quantity":0,"unitPrice":0,"amount":0},{"item":"Security Deposit","conditions":"","quantity":0,"unitPrice":300000,"amount":0}],"charterFee":445000,"unit":"WEEK"},"inclusionZones":[{"label":"Greece","type":"Sovereign country","category":["Europe","Southern Europe","Greece"],"coordinates":[24.261736188816826,38.42232351533858],"bbox":[19.646484375,34.934472656249994,28.231835937500023,41.743798828124994]}],"exclusionZones":[]},{"name":"14/09 -28/09","effectiveDates":[{"from":"2024-09-14T00:00:00.000Z","to":"2024-09-28T23:59:59.999Z"},{"from":"2025-09-14T00:00:00.000Z","to":"2025-09-28T23:59:59.999Z"},{"from":"2026-09-14T00:00:00.000Z","to":"2026-09-28T23:59:59.999Z"}],"pricing":{"note":"CHARTER RATES INCLUDE\nUse of yacht with her equipment • Yacht Insurance • VAT at current rate (discounted to 12%, subject to conditions) • Clean Linens (bed sheets & bath towels, 1 set per person per week, for up to 2 weeks max) • Outboard motor & first fill of gasoline • 1x full spare bottle of cooking gas • Berthing fees for first & last night at the marina/port • Final cleaning.","currency":"EUR","inputAmountTaxed":"INCLUSIVE","subTotal":395000,"totalTax":47400,"total":395000,"lineItems":[{"item":"Charter Fee","conditions":"","quantity":1,"unitPrice":395000,"amount":395000,"taxRate":{"label":"VAT","value":0.12}},{"item":"APA","conditions":"","quantity":0,"unitPrice":0,"amount":0},{"item":"Crew","conditions":"","quantity":0,"unitPrice":0,"amount":0},{"item":"Security Deposit","conditions":"","quantity":0,"unitPrice":300000,"amount":0}],"charterFee":395000,"unit":"WEEK"},"inclusionZones":[{"label":"Greece","type":"Sovereign country","category":["Europe","Southern Europe","Greece"],"coordinates":[24.261736188816826,38.42232351533858],"bbox":[19.646484375,34.934472656249994,28.231835937500023,41.743798828124994]}],"exclusionZones":[]},{"name":"28/09 -19/10","effectiveDates":[{"from":"2024-09-28T00:00:00.000Z","to":"2024-10-19T23:59:59.999Z"},{"from":"2025-09-28T00:00:00.000Z","to":"2025-10-19T23:59:59.999Z"},{"from":"2026-09-28T00:00:00.000Z","to":"2026-10-19T23:59:59.999Z"}],"pricing":{"note":"CHARTER RATES INCLUDE\nUse of yacht with her equipment • Yacht Insurance • VAT at current rate (discounted to 12%, subject to conditions) • Clean Linens (bed sheets & bath towels, 1 set per person per week, for up to 2 weeks max) • Outboard motor & first fill of gasoline • 1x full spare bottle of cooking gas • Berthing fees for first & last night at the marina/port • Final cleaning.","currency":"EUR","inputAmountTaxed":"INCLUSIVE","subTotal":295000,"totalTax":35400,"total":295000,"lineItems":[{"item":"Charter Fee","conditions":"","quantity":1,"unitPrice":295000,"amount":295000,"taxRate":{"label":"VAT","value":0.12}},{"item":"APA","conditions":"","quantity":0,"unitPrice":0,"amount":0},{"item":"Crew","conditions":"","quantity":0,"unitPrice":0,"amount":0},{"item":"Security Deposit","conditions":"","quantity":0,"unitPrice":300000,"amount":0}],"charterFee":295000,"unit":"WEEK"},"inclusionZones":[{"label":"Greece","type":"Sovereign country","category":["Europe","Southern Europe","Greece"],"coordinates":[24.261736188816826,38.42232351533858],"bbox":[19.646484375,34.934472656249994,28.231835937500023,41.743798828124994]}],"exclusionZones":[]},{"name":"19/10 -31/12","effectiveDates":[{"from":"2024-10-19T00:00:00.000Z","to":"2024-12-31T23:59:59.999Z"},{"from":"2025-10-19T00:00:00.000Z","to":"2025-12-31T23:59:59.999Z"},{"from":"2026-10-19T00:00:00.000Z","to":"2026-12-31T23:59:59.999Z"}],"pricing":{"currency":"EUR","inputAmountTaxed":"INCLUSIVE","subTotal":220000,"totalTax":26400,"total":220000,"note":"CHARTER RATES INCLUDE\nUse of yacht with her equipment • Yacht Insurance • VAT at current rate (discounted to 12%, subject to conditions) • Clean Linens (bed sheets & bath towels, 1 set per person per week, for up to 2 weeks max) • Outboard motor & first fill of gasoline • 1x full spare bottle of cooking gas • Berthing fees for first & last night at the marina/port • Final cleaning.","lineItems":[{"item":"Charter Fee","conditions":"","quantity":1,"unitPrice":220000,"amount":220000,"taxRate":{"label":"VAT","value":0.12}},{"item":"APA","conditions":"","quantity":0,"unitPrice":0,"amount":0},{"item":"Crew","conditions":"","quantity":0,"unitPrice":0,"amount":0},{"item":"Security Deposit","conditions":"","quantity":0,"unitPrice":300000,"amount":0}],"charterFee":220000,"unit":"WEEK"},"inclusionZones":[{"label":"Greece","type":"Sovereign country","category":["Europe","Southern Europe","Greece"],"coordinates":[24.261736188816826,38.42232351533858],"bbox":[19.646484375,34.934472656249994,28.231835937500023,41.743798828124994]}],"exclusionZones":[]}]}}