{"lastModified":1761293583121,"uri":"c::18230515995::vessel::d3329dd0-000d-11f0-811c-4b6b5a11ed95","yachtType":["Motor"],"description":"Operating Area: Greece\n\nDiscover the magic of the Fairline Squadron 55 \"ARCHON\". She promises to bring warmth and light to your journey as you explore the Aegean Sea and Greek islands. This sleek and stylish vessel offers a luxurious yacht experience, complete with all the amenities you need for a relaxing and memorable trip. From its spacious deck to its comfortable cabins, every inch of the Fairline Squadron \"ARCHON\" has been designed with your comfort and enjoyment in mind.","blueprint":{"name":"ARCHON","images":["/media/media::image::a::vessel::d3329dd0-000d-11f0-811c-4b6b5a11ed95::assets::7ace9100-0010-11f0-a47a-85976579a029/{imageVariant}","/media/media::image::a::vessel::d3329dd0-000d-11f0-811c-4b6b5a11ed95::assets::7aac14e0-0010-11f0-a47a-85976579a029/{imageVariant}","/media/media::image::a::vessel::d3329dd0-000d-11f0-811c-4b6b5a11ed95::assets::7a961be0-0010-11f0-a47a-85976579a029/{imageVariant}","/media/media::image::a::vessel::d3329dd0-000d-11f0-811c-4b6b5a11ed95::assets::7a892390-0010-11f0-a47a-85976579a029/{imageVariant}","/media/media::image::a::vessel::d3329dd0-000d-11f0-811c-4b6b5a11ed95::assets::7aefd4a0-0010-11f0-a47a-85976579a029/{imageVariant}","/media/media::image::a::vessel::d3329dd0-000d-11f0-811c-4b6b5a11ed95::assets::7ad68040-0010-11f0-a47a-85976579a029/{imageVariant}","/media/media::image::a::vessel::d3329dd0-000d-11f0-811c-4b6b5a11ed95::assets::7ac4cd00-0010-11f0-a47a-85976579a029/{imageVariant}"],"make":"Fairline Yachts","model":"Fairline 55","maxCrew":2,"sleeps":10,"basePort":{"uri":"a::place::319d8a50-5ccb-11f0-99fb-91ee55ccd7f1","name":"Kos Marina","coordinates":{"latitude":36.89133167221811,"longitude":27.30161579642024},"country":"Greece"},"cruisingCapacity":10,"staticCapacity":0,"builtYear":2002,"topSpeed":0,"fuelCapacity":2200,"cabinLayout":[{"label":"Double Cabins","value":"3"}],"cabins":3,"bathrooms":2,"length":16.54,"beam":4.65,"draft":2.21,"engines":"2 x VOLVO 449 KW","amenities":[{"label":"Air Conditioning"},{"label":"Bimini"},{"label":"Sprayhood"},{"label":"Cockpit Shower"},{"label":"Bowthruster"},{"label":"Inverter"},{"label":"Generator"},{"label":"GPS Plotter Outside"},{"label":"Autopilot"},{"label":"Fridge"},{"label":"Freezer"},{"label":"USB Ports (Salon and Cabins)"},{"label":"Gas Stove"},{"label":"Gas Oven"},{"label":"Espresso Maker"},{"label":""}],"toys":[{"label":"SUP","quantity":"2"},{"label":"Fishing gear ","quantity":"1"},{"label":"Snorkeling gear","quantity":"8"},{"label":"Sea scooter","quantity":"1"},{"label":"Kayak","quantity":"1"},{"label":"Life jackets (adults & kids)"},{"label":"Tube"},{"label":"Beach games"},{"label":"Board games: chess, UNO, card, backgammon"}],"entertainment":["Wi-Fi on Board","TV"]},"crew":[],"pricing":{"weekPricingFrom":{"currency":"EUR","price":1400000,"displayCurrency":"EUR","displayPrice":1400000,"unit":"WEEK"},"weekPricingTo":{"currency":"EUR","price":2100000,"displayCurrency":"EUR","displayPrice":2100000,"unit":"WEEK"},"pricingInfo":[{"name":"Low Season","effectiveDates":[{"from":"2026-01-01T00:00:00.000Z","to":"2026-06-30T23:59:59.999Z"},{"from":"2027-01-01T00:00:00.000Z","to":"2027-06-30T23:59:59.999Z"},{"from":"2028-01-01T00:00:00.000Z","to":"2028-06-30T23:59:59.999Z"},{"from":"2026-09-01T00:00:00.000Z","to":"2026-12-31T23:59:59.999Z"},{"from":"2027-09-01T00:00:00.000Z","to":"2027-12-31T23:59:59.999Z"},{"from":"2028-09-01T00:00:00.000Z","to":"2028-12-31T23:59:59.999Z"}],"pricing":{"currency":"EUR","charterFee":1400000,"inputAmountTaxed":"EXCLUSIVE","note":"","unit":"WEEK","lineItems":[{"item":"Charter Fee","quantity":1,"unitPrice":1400000,"amount":1400000,"conditions":"VAT & APA Excluded"}],"total":1400000,"subTotal":1400000,"totalTax":0},"inclusionZones":[{"label":"Greece","type":"Sovereign country","category":["Europe","Southern Europe","Greece"],"coordinates":[24.261736188816826,38.42232351533858],"bbox":[19.646484375,34.934472656249994,28.231835937500023,41.743798828124994]}],"exclusionZones":[],"petsAllowed":false},{"name":"High Season","effectiveDates":[{"from":"2026-07-01T00:00:00.000Z","to":"2026-08-31T23:59:59.999Z"},{"from":"2027-07-01T00:00:00.000Z","to":"2027-08-31T23:59:59.999Z"},{"from":"2028-07-01T00:00:00.000Z","to":"2028-08-31T23:59:59.999Z"}],"pricing":{"currency":"EUR","charterFee":2100000,"inputAmountTaxed":"EXCLUSIVE","note":"","unit":"WEEK","lineItems":[{"item":"Charter Fee","quantity":1,"unitPrice":2100000,"amount":2100000,"conditions":"VAT & APA Excluded"}],"total":2100000,"subTotal":2100000,"totalTax":0},"inclusionZones":[{"label":"Greece","type":"Sovereign country","category":["Europe","Southern Europe","Greece"],"coordinates":[24.261736188816826,38.42232351533858],"bbox":[19.646484375,34.934472656249994,28.231835937500023,41.743798828124994]}],"exclusionZones":[],"petsAllowed":false}]}}