{"lastModified":1768387266951,"uri":"c::7819240016::vessel::d5cbfb34-fe8c-11ed-889f-43d4bb723744","yachtType":["Sailing","Catamaran"],"description":"\nOperating Area: Naples, Sicily, Italy\n\nSIKELIA is a 16.80m / 55ft Catamaran Luxury Yacht built in 2020 by Catana. Sleeping 8 guests in 4 cabins and with a crew of 3. The guest cabins comprise a Master suite with a king size bed and en-suite bathroom facilities and 3 cabins with double beds and en-suite bathroom facilities.","blueprint":{"name":"SIKELIA","images":["/media/media::image::a::vessel::d5cbfb34-fe8c-11ed-889f-43d4bb723744::assets::0d65b750-e30b-11ef-b1c6-fbb7b2b3cafe/{imageVariant}","/media/media::image::a::vessel::d5cbfb34-fe8c-11ed-889f-43d4bb723744::assets::0d65de60-e30b-11ef-b1c7-fbb7b2b3cafe/{imageVariant}","/media/media::image::a::vessel::d5cbfb34-fe8c-11ed-889f-43d4bb723744::assets::0d662c81-e30b-11ef-b1c7-fbb7b2b3cafe/{imageVariant}","/media/media::image::a::vessel::d5cbfb34-fe8c-11ed-889f-43d4bb723744::assets::0d6987e0-e30b-11ef-9e6a-bb09122a793d/{imageVariant}","/media/media::image::a::vessel::d5cbfb34-fe8c-11ed-889f-43d4bb723744::assets::0d659040-e30b-11ef-b1c6-fbb7b2b3cafe/{imageVariant}","/media/media::image::a::vessel::d5cbfb34-fe8c-11ed-889f-43d4bb723744::assets::0d6430b0-e30b-11ef-b1c6-fbb7b2b3cafe/{imageVariant}","/media/media::image::a::vessel::d5cbfb34-fe8c-11ed-889f-43d4bb723744::assets::0d6457c0-e30b-11ef-b1c6-fbb7b2b3cafe/{imageVariant}","/media/media::image::a::vessel::d5cbfb34-fe8c-11ed-889f-43d4bb723744::assets::0d639470-e30b-11ef-b1c6-fbb7b2b3cafe/{imageVariant}","/media/media::image::a::vessel::d5cbfb34-fe8c-11ed-889f-43d4bb723744::assets::0d662c80-e30b-11ef-b1c7-fbb7b2b3cafe/{imageVariant}","/media/media::image::a::vessel::d5cbfb34-fe8c-11ed-889f-43d4bb723744::assets::0d6b5ca0-e30b-11ef-9f10-bda5dd88a35f/{imageVariant}","/media/media::image::a::vessel::d5cbfb34-fe8c-11ed-889f-43d4bb723744::assets::0d667aa0-e30b-11ef-b1c7-fbb7b2b3cafe/{imageVariant}","/media/media::image::a::vessel::d5cbfb34-fe8c-11ed-889f-43d4bb723744::assets::0d654220-e30b-11ef-b1c6-fbb7b2b3cafe/{imageVariant}","/media/media::image::a::vessel::d5cbfb34-fe8c-11ed-889f-43d4bb723744::assets::0d659040-e30b-11ef-b1c7-fbb7b2b3cafe/{imageVariant}","/media/media::image::a::vessel::d5cbfb34-fe8c-11ed-889f-43d4bb723744::assets::0d64ccf0-e30b-11ef-b1c6-fbb7b2b3cafe/{imageVariant}","/media/media::image::a::vessel::d5cbfb34-fe8c-11ed-889f-43d4bb723744::assets::0d6ae770-e30b-11ef-9f0f-bda5dd88a35f/{imageVariant}","/media/media::image::a::vessel::d5cbfb34-fe8c-11ed-889f-43d4bb723744::assets::0d6a4b30-e30b-11ef-9e6a-bb09122a793d/{imageVariant}","/media/media::image::a::vessel::d5cbfb34-fe8c-11ed-889f-43d4bb723744::assets::0d6ac060-e30b-11ef-9f10-bda5dd88a35f/{imageVariant}","/media/media::image::a::vessel::d5cbfb34-fe8c-11ed-889f-43d4bb723744::assets::0d6a7240-e30b-11ef-abb1-4733388c8535/{imageVariant}","/media/media::image::a::vessel::d5cbfb34-fe8c-11ed-889f-43d4bb723744::assets::0d66a1b0-e30b-11ef-b1c7-fbb7b2b3cafe/{imageVariant}","/media/media::image::a::vessel::d5cbfb34-fe8c-11ed-889f-43d4bb723744::assets::0d6bd1d0-e30b-11ef-abb1-4733388c8535/{imageVariant}"],"make":"Catana","model":"","maxCrew":3,"sleeps":8,"basePort":{"uri":"a::place::ca8a9a40-e050-11ed-9459-95e8090f12d7","name":"Capo d’Orlando","coordinates":{"latitude":38.16588801606285,"longitude":14.74635325361388},"country":"Italy"},"cruisingCapacity":0,"builtYear":2020,"cabinLayout":[{"label":"Master Cabin","value":"1"},{"label":"Double Cabin","value":"3"}],"cabins":4,"bathrooms":4,"length":16.8,"beam":8.74,"draft":1.48,"hullType":"Catamaran","superStructure":[],"engines":"2 x 80 hp Yanmar","amenities":[{"label":"Air Conditioning"},{"label":"Onboard WIFI"},{"label":"Salon TV"},{"label":"Salon Stereo"},{"label":"iPod/Device Hookups"},{"label":"Deck Shower"},{"label":"Children Allowed"},{"label":"Generator"},{"label":"Ice Maker"},{"label":"Inverter"},{"label":"Water Maker"},{"label":"Netflix"}],"toys":[{"label":"Snorkel Gear","quantity":"10"},{"label":"Jobe oasis water carpet","quantity":"1"},{"label":"SU Paddle Boards","quantity":"2"},{"label":"Fishing Gear"},{"label":"Yamaha Sea scooter","quantity":"1"},{"label":"Jobe Laysea (2 seat)","quantity":"1"},{"label":"Jobe Airstream","quantity":"1"}],"entertainment":["Onboard WIFI","Salon TV","Salon Stereo","iPod/Device Hookups","Netflix"],"tenders":["3.9m Tender with 30 HP engine"]},"crew":[],"pricing":{"weekPricingFrom":{"currency":"EUR","price":1300000,"displayCurrency":"EUR","displayPrice":1300000,"unit":"WEEK"},"weekPricingTo":{"currency":"EUR","price":2200000,"displayCurrency":"EUR","displayPrice":2200000,"unit":"WEEK"},"pricingInfo":[{"name":"20/09 - 31/12 & 24/05 - 13/06","effectiveDates":[{"from":"2025-09-20T00:00:00.000Z","to":"2025-12-31T23:59:59.999Z"},{"from":"2026-09-20T00:00:00.000Z","to":"2026-12-31T23:59:59.999Z"},{"from":"2027-09-20T00:00:00.000Z","to":"2027-12-31T23:59:59.999Z"},{"from":"2025-05-24T00:00:00.000Z","to":"2025-06-13T23:59:59.999Z"},{"from":"2026-05-24T00:00:00.000Z","to":"2026-06-13T23:59:59.999Z"},{"from":"2027-05-24T00:00:00.000Z","to":"2027-06-13T23:59:59.999Z"}],"pricing":{"currency":"EUR","charterFee":1350000,"inputAmountTaxed":"INCLUSIVE","note":"","unit":"WEEK","lineItems":[{"item":"Charter Fee","quantity":1,"unitPrice":1350000,"amount":1350000,"conditions":"Weekly"}],"total":1350000,"subTotal":1350000,"totalTax":0},"inclusionZones":[{"label":"Naples, Campania, Italy","type":"Custom Area","category":["Naples"],"coordinates":[14.5625,40.9125],"bbox":[14.025,40.683333,15.1,41.141667]},{"label":"Sicily","type":"Geo subunit","category":["Europe","Southern Europe","Sicily"],"coordinates":[14.155397130095018,37.59291213666052],"bbox":[12.435546875,36.687841796875,15.634667968750023,38.2958984375]}],"exclusionZones":[],"petsAllowed":false},{"name":"07/09 - 19/09 & 14/06 - 11/07","effectiveDates":[{"from":"2025-09-07T00:00:00.000Z","to":"2025-09-19T23:59:59.999Z"},{"from":"2026-09-07T00:00:00.000Z","to":"2026-09-19T23:59:59.999Z"},{"from":"2027-09-07T00:00:00.000Z","to":"2027-09-19T23:59:59.999Z"},{"from":"2025-06-14T00:00:00.000Z","to":"2025-07-11T23:59:59.999Z"},{"from":"2026-06-14T00:00:00.000Z","to":"2026-07-11T23:59:59.999Z"},{"from":"2027-06-14T00:00:00.000Z","to":"2027-07-11T23:59:59.999Z"}],"pricing":{"currency":"EUR","charterFee":1600000,"inputAmountTaxed":"INCLUSIVE","note":"","unit":"WEEK","lineItems":[{"item":"Charter Fee","quantity":1,"unitPrice":1600000,"amount":1600000,"conditions":"Weekly"}],"total":1600000,"subTotal":1600000,"totalTax":0},"inclusionZones":[{"label":"Naples, Campania, Italy","type":"Custom Area","category":["Naples"],"coordinates":[14.5625,40.9125],"bbox":[14.025,40.683333,15.1,41.141667]},{"label":"Sicily","type":"Geo subunit","category":["Europe","Southern Europe","Sicily"],"coordinates":[14.155397130095018,37.59291213666052],"bbox":[12.435546875,36.687841796875,15.634667968750023,38.2958984375]}],"exclusionZones":[],"petsAllowed":false},{"name":"23/08 - 06/09 & 12/07 - 25/07","effectiveDates":[{"from":"2025-08-23T00:00:00.000Z","to":"2025-09-06T23:59:59.999Z"},{"from":"2026-08-23T00:00:00.000Z","to":"2026-09-06T23:59:59.999Z"},{"from":"2027-08-23T00:00:00.000Z","to":"2027-09-06T23:59:59.999Z"},{"from":"2025-07-12T00:00:00.000Z","to":"2025-07-25T23:59:59.999Z"},{"from":"2026-07-12T00:00:00.000Z","to":"2026-07-25T23:59:59.999Z"},{"from":"2027-07-12T00:00:00.000Z","to":"2027-07-25T23:59:59.999Z"}],"pricing":{"currency":"EUR","charterFee":1900000,"inputAmountTaxed":"INCLUSIVE","note":"","unit":"WEEK","lineItems":[{"item":"Charter Fee","quantity":1,"unitPrice":1900000,"amount":1900000,"conditions":"Weekly"}],"total":1900000,"subTotal":1900000,"totalTax":0},"inclusionZones":[{"label":"Naples, Campania, Italy","type":"Custom Area","category":["Naples"],"coordinates":[14.5625,40.9125],"bbox":[14.025,40.683333,15.1,41.141667]},{"label":"Sicily","type":"Geo subunit","category":["Europe","Southern Europe","Sicily"],"coordinates":[14.155397130095018,37.59291213666052],"bbox":[12.435546875,36.687841796875,15.634667968750023,38.2958984375]}],"exclusionZones":[],"petsAllowed":false},{"name":"26/07 - 22/08","effectiveDates":[{"from":"2025-07-26T00:00:00.000Z","to":"2025-08-22T23:59:59.999Z"},{"from":"2026-07-26T00:00:00.000Z","to":"2026-08-22T23:59:59.999Z"},{"from":"2027-07-26T00:00:00.000Z","to":"2027-08-22T23:59:59.999Z"}],"pricing":{"currency":"EUR","charterFee":2200000,"inputAmountTaxed":"INCLUSIVE","note":"","unit":"WEEK","lineItems":[{"item":"Charter Fee","quantity":1,"unitPrice":2200000,"amount":2200000,"conditions":"Weekly"}],"total":2200000,"subTotal":2200000,"totalTax":0},"inclusionZones":[{"label":"Naples, Campania, Italy","type":"Custom Area","category":["Naples"],"coordinates":[14.5625,40.9125],"bbox":[14.025,40.683333,15.1,41.141667]},{"label":"Sicily","type":"Geo subunit","category":["Europe","Southern Europe","Sicily"],"coordinates":[14.155397130095018,37.59291213666052],"bbox":[12.435546875,36.687841796875,15.634667968750023,38.2958984375]}],"exclusionZones":[],"petsAllowed":false},{"name":"01/01 - 23/05","effectiveDates":[{"from":"2025-01-01T00:00:00.000Z","to":"2025-05-23T23:59:59.999Z"},{"from":"2026-01-01T00:00:00.000Z","to":"2026-05-23T23:59:59.999Z"},{"from":"2027-01-01T00:00:00.000Z","to":"2027-05-23T23:59:59.999Z"}],"pricing":{"currency":"EUR","charterFee":1300000,"inputAmountTaxed":"INCLUSIVE","note":"","unit":"WEEK","lineItems":[{"item":"Charter Fee","quantity":1,"unitPrice":1300000,"amount":1300000,"conditions":"Weekly"}],"total":1300000,"subTotal":1300000,"totalTax":0},"inclusionZones":[{"label":"Naples, Campania, Italy","type":"Custom Area","category":["Naples"],"coordinates":[14.5625,40.9125],"bbox":[14.025,40.683333,15.1,41.141667]},{"label":"Sicily","type":"Geo subunit","category":["Europe","Southern Europe","Sicily"],"coordinates":[14.155397130095018,37.59291213666052],"bbox":[12.435546875,36.687841796875,15.634667968750023,38.2958984375]}],"exclusionZones":[],"petsAllowed":false}]}}